dmf/__init__.py
dmf/match/__init__.py
dmf/match/matcher.py
dmf/preprocess/__init__.py
dmf/preprocess/data_preprocessor.py
dmf/preprocess/tokenizers.py
dmf/scores/__init__.py
dmf/scores/clusters.py
dmf/scores/similarities.py
dmf/scores/vectorizers.py
dmf/structures/__init__.py
dmf/structures/data.py
dmf/utils/__init__.py
dmf/utils/readers.py
dmf/utils/writers.py
match/__init__.py
match/matcher.py
matchingframework/__init__.py
matchingframework/match/__init__.py
matchingframework/match/matcher.py
matchingframework/preprocess/__init__.py
matchingframework/preprocess/data_preprocessor.py
matchingframework/preprocess/tokenizers.py
matchingframework/scores/__init__.py
matchingframework/scores/clusters.py
matchingframework/scores/similarities.py
matchingframework/scores/vectorizers.py
matchingframework/structures/__init__.py
matchingframework/structures/data.py
matchingframework/utils/__init__.py
matchingframework/utils/readers.py
matchingframework/utils/writers.py
preprocess/__init__.py
preprocess/data_preprocessor.py
preprocess/tokenizers.py
scores/__init__.py
scores/clusters.py
scores/similarities.py
scores/vectorizers.py
structures/__init__.py
structures/data.py
utils/__init__.py
utils/readers.py
utils/writers.py
matchingframework-0.5.1.dist-info/LICENSE
matchingframework-0.5.1.dist-info/METADATA
matchingframework-0.5.1.dist-info/WHEEL
matchingframework-0.5.1.dist-info/entry_points.txt
matchingframework-0.5.1.dist-info/top_level.txt
matchingframework-0.5.1.dist-info/RECORD
